ismn/__init__.py
ismn/base.py
ismn/citations.txt
ismn/cli.py
ismn/components.py
ismn/const.py
ismn/custom.py
ismn/filecollection.py
ismn/filehandlers.py
ismn/interface.py
ismn/meta.py
ismn-1.5.2.dist-info/AUTHORS.rst
ismn-1.5.2.dist-info/LICENSE.txt
ismn-1.5.2.dist-info/METADATA
ismn-1.5.2.dist-info/WHEEL
ismn-1.5.2.dist-info/entry_points.txt
ismn-1.5.2.dist-info/top_level.txt
ismn-1.5.2.dist-info/RECORD
