Metadata-Version: 2.2
Name: ismn
Version: 1.5.2
Summary: Readers for the data from the International Soil Moisture Database
Home-page: http://ismn.geo.tuwien.ac.at
Author: TU Wien
Author-email: support@qa4sm.eu
License: mit
Project-URL: Documentation, https://ismn.readthedocs.io/en/latest/
Platform: any
Classifier: Development Status :: 4 - Beta
Classifier: Programming Language :: Python
Requires-Python: >=3.6
License-File: LICENSE.txt
License-File: AUTHORS.rst
Requires-Dist: importlib-metadata; python_version < "3.8"
Requires-Dist: pygeogrids>=0.5.1
Requires-Dist: numpy
Requires-Dist: pandas
Requires-Dist: click
Requires-Dist: configparser
Requires-Dist: more_itertools
Requires-Dist: tqdm
Requires-Dist: repurpose>=0.11
Provides-Extra: plot
Requires-Dist: matplotlib; extra == "plot"
Requires-Dist: cartopy>=0.22; extra == "plot"
Requires-Dist: PyQt5; extra == "plot"
Provides-Extra: xr
Requires-Dist: xarray; extra == "xr"
Requires-Dist: dask; extra == "xr"
Provides-Extra: testing
Requires-Dist: pytest; extra == "testing"
Requires-Dist: pytest-cov; extra == "testing"
Requires-Dist: pytest-mpl; extra == "testing"
